datasette_rure/__init__.py
datasette_rure-0.3.dist-info/LICENSE
datasette_rure-0.3.dist-info/METADATA
datasette_rure-0.3.dist-info/WHEEL
datasette_rure-0.3.dist-info/entry_points.txt
datasette_rure-0.3.dist-info/top_level.txt
datasette_rure-0.3.dist-info/RECORD
