Metadata-Version: 2.1
Name: datasette-rure
Version: 0.3
Summary: Datasette plugin that adds a custom SQL function for executing matches using the Rust regular expression engine
Home-page: https://github.com/simonw/datasette-rure
Author: Simon Willison
License: Apache License, Version 2.0
Platform: UNKNOWN
Requires-Dist: datasette
Requires-Dist: rure
Provides-Extra: test
Requires-Dist: pytest ; extra == 'test'
